fusion_bench/__init__.py
fusion_bench/__main__.py
fusion_bench/py.typed
fusion_bench/_get_started/__init__.py
fusion_bench/_get_started/greeting_program.py
fusion_bench/compat/__init__.py
fusion_bench/compat/method/__init__.py
fusion_bench/compat/method/base_algorithm.py
fusion_bench/compat/modelpool/AutoModelForSeq2SeqLM.py
fusion_bench/compat/modelpool/__init__.py
fusion_bench/compat/modelpool/base_pool.py
fusion_bench/compat/modelpool/huggingface_clip_vision.py
fusion_bench/compat/taskpool/__init__.py
fusion_bench/compat/taskpool/base_pool.py
fusion_bench/compat/taskpool/clip_image_classification.py
fusion_bench/compat/taskpool/flan_t5_glue_text_generation.py
fusion_bench/constants/__init__.py
fusion_bench/constants/banner.py
fusion_bench/constants/clip_vision.py
fusion_bench/constants/paths.py
fusion_bench/constants/runtime.py
fusion_bench/dataset/__init__.py
fusion_bench/dataset/clip_dataset.py
fusion_bench/dataset/fer2013.py
fusion_bench/dataset/gpt2_glue.py
fusion_bench/dataset/gsm8k.py
fusion_bench/dataset/image_dataset.py
fusion_bench/dataset/imdb.py
fusion_bench/dataset/nyuv2.py
fusion_bench/dataset/arc_agi/__init__.py
fusion_bench/dataset/arc_agi/arc.py
fusion_bench/dataset/arc_agi/arc_agi.py
fusion_bench/dataset/arc_agi/augmenters.py
fusion_bench/dataset/arc_agi/messagers.py
fusion_bench/dataset/arc_agi/np_cache.py
fusion_bench/dataset/arc_agi/preprocess.py
fusion_bench/dataset/arc_agi/representers.py
fusion_bench/dataset/image_corruption/__init__.py
fusion_bench/dataset/image_corruption/make_corruption.py
fusion_bench/dataset/llama/__init__.py
fusion_bench/dataset/llama/alpaca.py
fusion_bench/dataset/llama/collate.py
fusion_bench/dataset/llama/metamathqa.py
fusion_bench/dataset/llama/openai.py
fusion_bench/dataset/llama/preference_700k.py
fusion_bench/dataset/llama/sharegpt.py
fusion_bench/dataset/llama/squad.py
fusion_bench/dataset/llama/stanford_shp.py
fusion_bench/dataset/llama/ultrachat.py
fusion_bench/dataset/llama/wikitext.py
fusion_bench-0.2.31.dist-info/licenses/LICENSE
fusion_bench-0.2.31.dist-info/METADATA
fusion_bench-0.2.31.dist-info/WHEEL
fusion_bench-0.2.31.dist-info/entry_points.txt
fusion_bench-0.2.31.dist-info/top_level.txt
fusion_bench-0.2.31.dist-info/RECORD
