Metadata-Version: 2.4
Name: fusion-bench
Version: 0.2.31
Summary: A Comprehensive Benchmark of Deep Model Fusion
Author-email: Anke Tang <tang.anke@foxmail.com>
Project-URL: Repository, https://github.com/tanganke/fusion_bench
Project-URL: Homepage, https://github.com/tanganke/fusion_bench
Project-URL: Issues, https://github.com/tanganke/fusion_bench/issues
Keywords: deep learning,model fusion,benchmark
Requires-Python: >=3.10
License-File: LICENSE
Requires-Dist: hydra-core
Requires-Dist: lightning
Requires-Dist: transformers
Requires-Dist: datasets
Requires-Dist: peft
Requires-Dist: huggingface_hub
Requires-Dist: matplotlib
Requires-Dist: tensorboard
Requires-Dist: tqdm
Requires-Dist: rich
Requires-Dist: scipy
Requires-Dist: h5py
Requires-Dist: pytest
Requires-Dist: joblib
Requires-Dist: bidict
Requires-Dist: transformers!=4.49
Requires-Dist: pillow!=11.2.1
Provides-Extra: lm-eval-harness
Requires-Dist: lm-eval; extra == "lm-eval-harness"
Requires-Dist: immutabledict; extra == "lm-eval-harness"
Requires-Dist: langdetect; extra == "lm-eval-harness"
Requires-Dist: rich-run; extra == "lm-eval-harness"
Provides-Extra: docs
Requires-Dist: mkdocs; extra == "docs"
Requires-Dist: mkdocs-material; extra == "docs"
Requires-Dist: mkdocstrings[python]; extra == "docs"
Dynamic: license-file
